{
  "loc": 18134,
  "tests": 461,
  "testFiles": 26,
  "commits": 137,
  "contributors": 2,
  "firstCommit": "2026-03-07",
  "languages": [
    {
      "name": "TypeScript",
      "bytes": 417775,
      "percent": 46
    },
    {
      "name": "Python",
      "bytes": 355953,
      "percent": 40
    },
    {
      "name": "HTML",
      "bytes": 117181,
      "percent": 13
    }
  ],
  "fixes": {
    "count": 29
  },
  "linesRefactored": {
    "count": 1568
  },
  "prs": {
    "merged": 64
  },
  "repo": "Jason-Vaughan/Notse",
  "branch": "main",
  "source": "git",
  "private": true,
  "archived": false,
  "updatedAt": "2026-05-11T07:42:01.936Z"
}
